{
  "id": "article-004",
  "title": {
    "zh": "平假名有多少个？完整的平假名字符数量解析",
    "ja": "ひらがなはいくつある？完全なひらがな文字数の解析",
    "en": "How Many Hiragana Are There? Complete Analysis of Hiragana Character Count"
  },
  "author": {
    "zh": "日语专家",
    "ja": "日本語専門家",
    "en": "Japanese Expert"
  },
  "desc": {
    "zh": "详细解析平假名的数量，包括基本假名、浊音、半浊音和拗音，帮助学习者全面了解平假名体系。",
    "ja": "基本仮名、濁音、半濁音、拗音を含むひらがなの数を詳しく解析し、学習者がひらがなシステムを包括的に理解できるよう支援します。",
    "en": "Detailed analysis of the number of hiragana characters, including basic kana, dakuten, handakuten, and yōon, helping learners comprehensively understand the hiragana system."
  },
  "updateTime": "2025-05-20",
  "tags": {
    "zh": ["平假名", "字符数量", "基础知识", "日语学习"],
    "ja": ["ひらがな", "文字数", "基礎知識", "日本語学習"],
    "en": ["Hiragana", "Character Count", "Basics", "Japanese Learning"]
  },
  "content": {
    "zh": "# 平假名有多少个？完整的平假名字符数量解析\n\n对于日语学习者来说，了解平假名的确切数量是掌握日语文字系统的重要一步。让我们来详细分析一下平假名到底有多少个字符。\n\n## 基本平假名：46个\n\n传统的五十音图包含**46个基本平假名**：\n\n### 清音（46个）\n\n| 行 | あ段 | い段 | う段 | え段 | お段 |\n|---|-----|-----|-----|-----|-----|\n| あ行 | あ | い | う | え | お |\n| か行 | か | き | く | け | こ |\n| さ行 | さ | し | す | せ | そ |\n| た行 | た | ち | つ | て | と |\n| な行 | な | に | ぬ | ね | の |\n| は行 | は | ひ | ふ | へ | ほ |\n| ま行 | ま | み | む | め | も |\n| や行 | や | - | ゆ | - | よ |\n| ら行 | ら | り | る | れ | ろ |\n| わ行 | わ | - | - | - | を |\n| ん | ん | - | - | - | - |\n\n注意：や行和わ行中的一些位置是空的，这就是为什么叫\"五十音\"但实际只有46个字符的原因。\n\n## 浊音和半浊音：25个\n\n### 浊音（20个）\n通过在清音上添加浊音符号（゛）形成：\n\n- **が行**：が、ぎ、ぐ、げ、ご（5个）\n- **ざ行**：ざ、じ、ず、ぜ、ぞ（5个）\n- **だ行**：だ、ぢ、づ、で、ど（5个）\n- **ば行**：ば、び、ぶ、べ、ぼ（5个）\n\n### 半浊音（5个）\n通过在は行上添加半浊音符号（゜）形成：\n\n- **ぱ行**：ぱ、ぴ、ぷ、ぺ、ぽ（5个）\n\n## 拗音：33个\n\n拗音是由い段假名（き、し、ち、に、ひ、み、り、ぎ、じ、び、ぴ）与小写的や、ゆ、よ组合而成：\n\n### 清音拗音（21个）\n- きゃ、きゅ、きょ\n- しゃ、しゅ、しょ\n- ちゃ、ちゅ、ちょ\n- にゃ、にゅ、にょ\n- ひゃ、ひゅ、ひょ\n- みゃ、みゅ、みょ\n- りゃ、りゅ、りょ\n\n### 浊音拗音（12个）\n- ぎゃ、ぎゅ、ぎょ\n- じゃ、じゅ、じょ\n- びゃ、びゅ、びょ\n- ぴゃ、ぴゅ、ぴょ\n\n## 总计：104个平假名字符\n\n让我们来总结一下：\n\n- **基本清音**：46个\n- **浊音**：20个\n- **半浊音**：5个\n- **拗音**：33个\n\n**总计：104个平假名字符**\n\n## 实际使用中的考虑\n\n### 常用程度\n虽然总共有104个平假名字符，但在日常使用中：\n\n1. **最基础的46个清音**是必须掌握的\n2. **浊音和半浊音25个**也很常用\n3. **拗音33个**在某些词汇中会用到\n\n### 学习建议\n\n1. **第一阶段**：掌握46个基本清音\n2. **第二阶段**：学习25个浊音和半浊音\n3. **第三阶段**：熟悉33个拗音\n\n## 与片假名的对比\n\n值得注意的是，片假名的数量与平假名完全相同，也是104个字符，只是书写形式不同。\n\n## 结论\n\n平假名总共有**104个字符**，包括46个基本字符、25个浊音/半浊音字符，以及33个拗音字符。对于初学者来说，建议循序渐进地学习，先掌握基本的46个字符，再逐步扩展到完整的104个字符体系。\n\n记住，虽然数量看起来很多，但通过系统的学习和练习，完全可以掌握所有的平假名字符！",
    "ja": "# ひらがなはいくつある？完全なひらがな文字数の解析\n\n日本語学習者にとって、ひらがなの正確な数を知ることは、日本語の文字体系を理解する重要な一歩です。ひらがなが実際にいくつあるのか、詳しく分析してみましょう。\n\n## 基本ひらがな：46文字\n\n伝統的な五十音図には**46の基本ひらがな**が含まれています：\n\n### 清音（46文字）\n\n| 行 | あ段 | い段 | う段 | え段 | お段 |\n|---|-----|-----|-----|-----|-----|\n| あ行 | あ | い | う | え | お |\n| か行 | か | き | く | け | こ |\n| さ行 | さ | し | す | せ | そ |\n| た行 | た | ち | つ | て | と |\n| な行 | な | に | ぬ | ね | の |\n| は行 | は | ひ | ふ | へ | ほ |\n| ま行 | ま | み | む | め | も |\n| や行 | や | - | ゆ | - | よ |\n| ら行 | ら | り | る | れ | ろ |\n| わ行 | わ | - | - | - | を |\n| ん | ん | - | - | - | - |\n\n注意：や行とわ行の一部の位置は空いており、これが「五十音」と呼ばれながら実際には46文字しかない理由です。\n\n## 濁音と半濁音：25文字\n\n### 濁音（20文字）\n清音に濁点（゛）を付けて形成：\n\n- **が行**：が、ぎ、ぐ、げ、ご（5文字）\n- **ざ行**：ざ、じ、ず、ぜ、ぞ（5文字）\n- **だ行**：だ、ぢ、づ、で、ど（5文字）\n- **ば行**：ば、び、ぶ、べ、ぼ（5文字）\n\n### 半濁音（5文字）\nは行に半濁点（゜）を付けて形成：\n\n- **ぱ行**：ぱ、ぴ、ぷ、ぺ、ぽ（5文字）\n\n## 拗音：33文字\n\n拗音はい段の仮名（き、し、ち、に、ひ、み、り、ぎ、じ、び、ぴ）と小さなや、ゆ、よの組み合わせで形成：\n\n### 清音拗音（21文字）\n- きゃ、きゅ、きょ\n- しゃ、しゅ、しょ\n- ちゃ、ちゅ、ちょ\n- にゃ、にゅ、にょ\n- ひゃ、ひゅ、ひょ\n- みゃ、みゅ、みょ\n- りゃ、りゅ、りょ\n\n### 濁音拗音（12文字）\n- ぎゃ、ぎゅ、ぎょ\n- じゃ、じゅ、じょ\n- びゃ、びゅ、びょ\n- ぴゃ、ぴゅ、ぴょ\n\n## 合計：104のひらがな文字\n\nまとめてみましょう：\n\n- **基本清音**：46文字\n- **濁音**：20文字\n- **半濁音**：5文字\n- **拗音**：33文字\n\n**合計：104のひらがな文字**\n\n## 実際の使用における考慮事項\n\n### 使用頻度\n合計104のひらがな文字がありますが、日常使用では：\n\n1. **最も基本的な46の清音**は必須\n2. **濁音と半濁音25文字**もよく使用される\n3. **拗音33文字**は特定の語彙で使用される\n\n### 学習のアドバイス\n\n1. **第一段階**：46の基本清音をマスター\n2. **第二段階**：25の濁音と半濁音を学習\n3. **第三段階**：33の拗音に慣れる\n\n## カタカナとの比較\n\n注目すべきは、カタカナの数もひらがなと全く同じ104文字で、書き方が異なるだけです。\n\n## 結論\n\nひらがなは合計**104文字**あり、46の基本文字、25の濁音/半濁音文字、33の拗音文字が含まれます。初学者には段階的な学習をお勧めし、まず基本の46文字をマスターしてから、完全な104文字体系に拡張していくことが大切です。\n\n数が多く見えるかもしれませんが、体系的な学習と練習により、すべてのひらがな文字を完全にマスターすることができます！",
    "en": "# How Many Hiragana Are There? Complete Analysis of Hiragana Character Count\n\nFor Japanese learners, understanding the exact number of hiragana characters is an important step in mastering the Japanese writing system. Let's analyze in detail how many hiragana characters there actually are.\n\n## Basic Hiragana: 46 Characters\n\nThe traditional Gojuon chart contains **46 basic hiragana characters**:\n\n### Seion (Clear Sounds) - 46 Characters\n\n| Row | あ-dan | い-dan | う-dan | え-dan | お-dan |\n|-----|--------|--------|--------|--------|--------|\n| あ-gyō | あ | い | う | え | お |\n| か-gyō | か | き | く | け | こ |\n| さ-gyō | さ | し | す | せ | そ |\n| た-gyō | た | ち | つ | て | と |\n| な-gyō | な | に | ぬ | ね | の |\n| は-gyō | は | ひ | ふ | へ | ほ |\n| ま-gyō | ま | み | む | め | も |\n| や-gyō | や | - | ゆ | - | よ |\n| ら-gyō | ら | り | る | れ | ろ |\n| わ-gyō | わ | - | - | - | を |\n| ん | ん | - | - | - | - |\n\nNote: Some positions in the ya-gyō and wa-gyō rows are empty, which is why it's called \"fifty sounds\" but actually contains only 46 characters.\n\n## Dakuten and Handakuten: 25 Characters\n\n### Dakuten (Voiced Sounds) - 20 Characters\nFormed by adding dakuten marks (゛) to seion:\n\n- **が-gyō**: が、ぎ、ぐ、げ、ご (5 characters)\n- **ざ-gyō**: ざ、じ、ず、ぜ、ぞ (5 characters)\n- **だ-gyō**: だ、ぢ、づ、で、ど (5 characters)\n- **ば-gyō**: ば、び、ぶ、べ、ぼ (5 characters)\n\n### Handakuten (Semi-voiced Sounds) - 5 Characters\nFormed by adding handakuten marks (゜) to ha-gyō:\n\n- **ぱ-gyō**: ぱ、ぴ、ぷ、ぺ、ぽ (5 characters)\n\n## Yōon (Contracted Sounds): 33 Characters\n\nYōon are formed by combining i-dan kana (き、し、ち、に、ひ、み、り、ぎ、じ、び、ぴ) with small や、ゆ、よ:\n\n### Seion Yōon (21 characters)\n- きゃ、きゅ、きょ\n- しゃ、しゅ、しょ\n- ちゃ、ちゅ、ちょ\n- にゃ、にゅ、にょ\n- ひゃ、ひゅ、ひょ\n- みゃ、みゅ、みょ\n- りゃ、りゅ、りょ\n\n### Dakuten Yōon (12 characters)\n- ぎゃ、ぎゅ、ぎょ\n- じゃ、じゅ、じょ\n- びゃ、びゅ、びょ\n- ぴゃ、ぴゅ、ぴょ\n\n## Total: 104 Hiragana Characters\n\nLet's summarize:\n\n- **Basic seion**: 46 characters\n- **Dakuten**: 20 characters\n- **Handakuten**: 5 characters\n- **Yōon**: 33 characters\n\n**Total: 104 hiragana characters**\n\n## Practical Usage Considerations\n\n### Frequency of Use\nWhile there are 104 hiragana characters in total, in daily usage:\n\n1. **The most basic 46 seion** are essential to master\n2. **25 dakuten and handakuten** are also commonly used\n3. **33 yōon** are used in specific vocabulary\n\n### Learning Recommendations\n\n1. **Stage 1**: Master the 46 basic seion\n2. **Stage 2**: Learn the 25 dakuten and handakuten\n3. **Stage 3**: Familiarize with the 33 yōon\n\n## Comparison with Katakana\n\nIt's worth noting that katakana has exactly the same number as hiragana - 104 characters - just written in different forms.\n\n## Conclusion\n\nHiragana consists of **104 characters** in total, including 46 basic characters, 25 dakuten/handakuten characters, and 33 yōon characters. For beginners, it's recommended to learn progressively, first mastering the basic 46 characters before expanding to the complete 104-character system.\n\nRemember, while the number may seem large, through systematic learning and practice, you can completely master all hiragana characters!"
  }
}